{"usuarios":[{"nome":"estela da silva magalhaes","email":"estelinha.mag@hotmail.com","senha":"123","confirma_senha":"123","caminhofoto":"images\/fotosUsuario\/luigi.jpg"},
  {"nome":"estela da silva magalhaes","email":"estelinha.mag@hotmail.com","senha":"$2y$10$tzZSLGc0VBo.yXp7SdeM..7K3ddcQddKKx5j7TINXf6Ytp.fToyQq","confirma_senha":"123","caminhofoto":"images\/fotosUsuario\/batman.jpg"},
  {"nome":"estela da silva magalhaes","email":"estelinha.mag@hotmail.com","senha":"$2y$10$mHtAgKKUt1.gDziW2DYDeOqSgM8A4GwdqqcwfYoqTvOz65igkMZ7q","confirma_senha":"123","caminhofoto":"images\/fotosUsuario\/captainamerica.jpg"}]}
